app/__init__.py
app/asgi.py
app/forms.py
app/settings.py
app/urls.py
app/wsgi.py
oc_2_python_app-0.1.1.dist-info/licenses/LICENSE
oc_2_python_app-0.1.1.dist-info/METADATA
oc_2_python_app-0.1.1.dist-info/WHEEL
oc_2_python_app-0.1.1.dist-info/top_level.txt
oc_2_python_app-0.1.1.dist-info/RECORD
