Metadata-Version: 2.4
Name: oc-2-python-app
Version: 0.1.1
Summary: A landing page Python app called "StartupX" that runs on Django. It contains a home, about, features, and a contact page.
Author: oc-2
License: MIT License
Project-URL: Source, https://github.com/oc-2/python-app
Project-URL: Issues, https://github.com/oc-2/python-app/issues
Keywords: python,django,landing page
Classifier: Environment :: Web Environment
Classifier: Framework :: Django
Classifier: Framework :: Django :: 5.0
Classifier: License :: OSI Approved :: MIT License
Classifier: Natural Language :: English
Classifier: Operating System :: OS Independent
Classifier: Programming Language :: Python
Classifier: Programming Language :: Python :: 3.11
Classifier: Programming Language :: Python :: 3.12
Classifier: Programming Language :: Python :: 3.13
Classifier: Topic :: Internet :: WWW/HTTP
Classifier: Topic :: Internet :: WWW/HTTP :: Dynamic Content
Classifier: Topic :: Internet :: WWW/HTTP :: WSGI
Classifier: Topic :: Software Development :: Libraries :: Application Frameworks
Classifier: Topic :: Software Development :: Libraries :: Python Modules
Requires-Python: >=3.12
License-File: LICENSE
Requires-Dist: asgiref==3.10.0
Requires-Dist: build==1.3.0
Requires-Dist: distlib==0.4.0
Requires-Dist: Django==5.2.8
Requires-Dist: filelock==3.20.0
Requires-Dist: packaging==25.0
Requires-Dist: platformdirs==4.5.0
Requires-Dist: pyproject_hooks==1.2.0
Requires-Dist: setuptools==80.9.0
Requires-Dist: sqlparse==0.5.3
Requires-Dist: wheel==0.45.1
Dynamic: license-file
